PrixCarburantClient-1.0.5.dist-info/DESCRIPTION.rst
PrixCarburantClient-1.0.5.dist-info/METADATA
PrixCarburantClient-1.0.5.dist-info/RECORD
PrixCarburantClient-1.0.5.dist-info/WHEEL
PrixCarburantClient-1.0.5.dist-info/entry_points.txt
PrixCarburantClient-1.0.5.dist-info/metadata.json
PrixCarburantClient-1.0.5.dist-info/top_level.txt
prixCarburantClient/prixCarburantClient.py
