Metadata-Version: 2.0
Name: PrixCarburantClient
Version: 1.0.5
Summary: StationEssence client 
Home-page: https://github.com/max5962/essence
Author: Maxime Wantiez
Author-email: 
License: MIT
Platform: UNKNOWN
